{
    "version": 1,
    "rules": [
        {
            "domain": [
                "o4504926511693824.ingest.sentry.io",
                "github-api.arkoselabs.com",
                "nvidia.tt.omtrdc.net",
                "github-cloud.s3.amazonaws.com"
            ]
        },
        {
            "domain_suffix": [
                "tegrazone.jp",
                "nvidia.com.pl",
                "shotwithgeforce.com",
                "nvidia.com.au",
                "nvidia.cz",
                "nvidia.eu",
                "nvidia.com.ve",
                "nvidia.co.kr",
                "mega.nz",
                "mypikpak.com",
                "anaconda.org",
                "pikpakdrive.com",
                "nvidia.ch",
                "nvidia.in",
                "anaconda.com",
                "nvidia.it",
                "npmjs.com",
                "tegrazone.co",
                "nvidia.de",
                "repo.new",
                "githubhackathon.com",
                "anaconda.cloud",
                "githubcopilot.com",
                "github.blog",
                "mega.co.nz",
                "nvidia.com.br",
                "nvidia.dk",
                "nvidia.asia",
                "nvidia.jp",
                "pypi.org",
                "geforce.com",
                "conda.io",
                "nvidia.com.mx",
                "mega.io",
                "githubnext.com",
                "pickpackapp.com",
                "githubstatus.com",
                "nvidiagrid.net",
                "github.community",
                "pikpak.io",
                "nvidia.tw",
                "ubuntuforums.org",
                "dependabot.com",
                "github.io",
                "npmjs.org",
                "ubuntu.com",
                "atom.io",
                "gputechconf.co.kr",
                "ubuntu.net",
                "mypikpak.net",
                "pypa.io",
                "github.ai",
                "gh.io",
                "nvidia.ru",
                "github.com",
                "githubuniverse.com",
                "geforce.co.kr",
                "blob.core.windows.net",
                "git.io",
                "nvidia.at",
                "pypi.io",
                "nvidia.nl",
                "octocaptcha.com",
                "githubpreview.dev",
                "nvidia.mx",
                "opensource.guide",
                "nvidia.co.at",
                "nvidia.co.jp",
                "copilot-telemetry.githubusercontent.com",
                "myoctocat.com",
                "nvidia.se",
                "gputechconf.eu",
                "pycon.org",
                "tegrazone.co.kr",
                "thegithubshop.com",
                "geforce.com.tw",
                "nvidia.fi",
                "nvidia.lu",
                "gputechconf.cn",
                "python.org",
                "nvidiaforhp.com",
                "tegrazone.kr",
                "github.dev",
                "nvidia.ro",
                "nvidia.be",
                "npm.community",
                "nvidia.no",
                "nvidia.com",
                "tegrazone.com",
                "geforce.cn",
                "githubassets.com",
                "collector.github.com",
                "gputechconf.com.au",
                "nvidia.cn",
                "ubuntu-touch.io",
                "nvidia.com.ua",
                "nvidia.com.tr",
                "nvidia.es",
                "ghcr.io",
                "nvidia.co.uk",
                "pythonhosted.org",
                "geforce.co.uk",
                "nvidia.com.pe",
                "gputechconf.jp",
                "nvidia.pl",
                "nvidia.co.in",
                "pikpak.me",
                "githubusercontent.com",
                "gputechconf.in",
                "gputechconf.com",
                "gputechconf.com.tw",
                "nvidia.fr",
                "nvidia.com.tw",
                "githubapp.com"
            ]
        },
        {
            "domain_regex": [
                "^github-production-release-asset-[0-9a-zA-Z]{6}\\.s3\\.amazonaws\\.com$"
            ]
        }
    ]
}