{
    "version": 1,
    "rules": [
        {
            "domain": [
                "time1.cloud.tencent.com",
                "stun.l.google.com",
                "amobile.music.tc.qq.com",
                "mobileoc.music.tc.qq.com",
                "isure.stream.qqmusic.qq.com",
                "lens.l.google.com",
                "api-jooxtt.sanook.com",
                "songsearch.kugou.com",
                "swcdn.apple.com",
                "static.adtidy.org",
                "music.taihe.com",
                "mesu.apple.com",
                "aqqmusic.tc.qq.com",
                "joox.com",
                "anti-ad.net",
                "streamoc.music.tc.qq.com",
                "swdownload.apple.com",
                "musicapi.taihe.com",
                "trackercdn.kugou.com",
                "dl.stream.qqmusic.qq.com",
                "swdist.apple.com",
                "heartbeat.belkin.com",
                "xnotify.xboxlive.com",
                "api.joox.com",
                "swquery.apple.com",
                "adrules.top",
                "ps.res.netease.com",
                "adguardteam.github.io",
                "na.b.g-tun.com",
                "shark007.net",
                "localhost.sec.qq.com",
                "proxy.golang.org",
                "local.adguard.org",
                "time-ios.apple.com",
                "localhost.ptlogin2.qq.com",
                "ff.dorado.sdo.com",
                "swscan.apple.com"
            ]
        },
        {
            "domain_suffix": [
                "kuwo.cn",
                "stun.playstation.net",
                "linksyssmartwifi.com",
                "router.asus.com",
                "y.qq.com",
                "time.edu.cn",
                "uu.163.com",
                "direct",
                "3gppnetwork.org",
                "battlenet.com.cn",
                "music.migu.cn",
                "orayimg.com",
                "lan",
                "invalid",
                "n0808.com",
                "finalfantasyxiv.com",
                "home.arpa",
                "oray.com",
                "steamcontent.com",
                "square-enix.com",
                "msftconnecttest.com",
                "msftncsi.com",
                "wargaming.net",
                "gcloudsdk.com",
                "wowsgame.cn",
                "pool.ntp.org",
                "xiami.com",
                "126.net",
                "gcloudcs.com",
                "cdn.nintendo.net",
                "cmbimg.com",
                "localdomain",
                "ffxiv.com",
                "localhost",
                "linksys.com",
                "ff14.sdo.com",
                "local",
                "music.163.com",
                "market.xiaomi.com",
                "nflxvideo.net",
                "sandai.net",
                "cmbchina.com",
                "wggames.cn",
                "wotgame.cn",
                "media.dssott.com",
                "srv.nintendo.net",
                "example",
                "battle.net",
                "ntp.org.cn",
                "test",
                "mcdn.bilivideo.cn"
            ]
        },
        {
            "domain_regex": [
                "ntp7.*.com",
                "stun.*.*.*",
                "xbox.*.*.microsoft.com",
                ".+.stun.*.*.*.*",
                "ntp5.*.com",
                "time.*.apple.com",
                "ntp.*.com",
                "ntp3.*.com",
                "xbox.*.microsoft.com",
                "time4.*.com",
                ".+.stun.*.*.*.*.*",
                "time2.*.com",
                ".+.stun.*.*.*",
                "time7.*.com",
                "time.*.com",
                "ntp2.*.com",
                ".+.stun.*.*",
                "localhost.*.weixin.qq.com",
                "ntp6.*.com",
                "time5.*.com",
                "stun.*.*",
                "time1.*.com",
                "time.*.gov",
                "time.*.edu.cn",
                ".*.*.xboxlive.com",
                "ntp4.*.com",
                "time6.*.com",
                "time3.*.com",
                "ntp1.*.com"
            ]
        }
    ]
}