{
    "version": 1,
    "rules": [
        {
            "domain": [
                "na.b.g-tun.com",
                "mobileoc.music.tc.qq.com",
                "songsearch.kugou.com",
                "mesu.apple.com",
                "proxy.golang.org",
                "ff.dorado.sdo.com",
                "swscan.apple.com",
                "api.joox.com",
                "swdownload.apple.com",
                "musicapi.taihe.com",
                "streamoc.music.tc.qq.com",
                "adguardteam.github.io",
                "local.adguard.org",
                "heartbeat.belkin.com",
                "api-jooxtt.sanook.com",
                "shark007.net",
                "swcdn.apple.com",
                "dl.stream.qqmusic.qq.com",
                "static.adtidy.org",
                "trackercdn.kugou.com",
                "joox.com",
                "adrules.top",
                "anti-ad.net",
                "aqqmusic.tc.qq.com",
                "time1.cloud.tencent.com",
                "swquery.apple.com",
                "xnotify.xboxlive.com",
                "lens.l.google.com",
                "localhost.sec.qq.com",
                "music.taihe.com",
                "time-ios.apple.com",
                "localhost.ptlogin2.qq.com",
                "swdist.apple.com",
                "isure.stream.qqmusic.qq.com",
                "ps.res.netease.com",
                "amobile.music.tc.qq.com"
            ]
        },
        {
            "domain_suffix": [
                "srv.nintendo.net",
                "mcdn.bilivideo.cn",
                "y.qq.com",
                "battle.net",
                "cmbchina.com",
                "media.dssott.com",
                "linksyssmartwifi.com",
                "ntp.org.cn",
                "music.migu.cn",
                "test",
                "oray.com",
                "uu.163.com",
                "wowsgame.cn",
                "local",
                "localhost",
                "cmbimg.com",
                "time.edu.cn",
                "msftncsi.com",
                "msftconnecttest.com",
                "kuwo.cn",
                "direct",
                "finalfantasyxiv.com",
                "sandai.net",
                "wotgame.cn",
                "steamcontent.com",
                "linksys.com",
                "cdn.nintendo.net",
                "gcloudcs.com",
                "kk-rays.com",
                "market.xiaomi.com",
                "orayimg.com",
                "battlenet.com.cn",
                "square-enix.com",
                "wggames.cn",
                "xiami.com",
                "126.net",
                "3gppnetwork.org",
                "localdomain",
                "router.asus.com",
                "wargaming.net",
                "example",
                "n0808.com",
                "music.163.com",
                "lan",
                "pool.ntp.org",
                "home.arpa",
                "ff14.sdo.com",
                "ffxiv.com",
                "invalid"
            ]
        },
        {
            "domain_regex": [
                "^Mijia\\sCloud$",
                "^xbox\\.[^.]+\\.microsoft\\.com$",
                "^[^.]+\\.[^.]+\\.xboxlive\\.com$",
                "^[^.]+$",
                "^xbox\\.[^.]+\\.[^.]+\\.microsoft\\.com$",
                "^localhost\\.[^.]+\\.weixin\\.qq\\.com$"
            ]
        }
    ]
}